pyprocessors_opennre/__init__.py
pyprocessors_opennre/opennre_proc.py
pyprocessors_opennre/opennre/__init__.py
pyprocessors_opennre/opennre/pretrain.py
pyprocessors_opennre/opennre/encoder/__init__.py
pyprocessors_opennre/opennre/encoder/base_encoder.py
pyprocessors_opennre/opennre/encoder/bert_encoder.py
pyprocessors_opennre/opennre/encoder/cnn_encoder.py
pyprocessors_opennre/opennre/encoder/pcnn_encoder.py
pyprocessors_opennre/opennre/framework/__init__.py
pyprocessors_opennre/opennre/framework/bag_re.py
pyprocessors_opennre/opennre/framework/data_loader.py
pyprocessors_opennre/opennre/framework/multi_label_sentence_re.py
pyprocessors_opennre/opennre/framework/sentence_re.py
pyprocessors_opennre/opennre/framework/utils.py
pyprocessors_opennre/opennre/model/__init__.py
pyprocessors_opennre/opennre/model/bag_attention.py
pyprocessors_opennre/opennre/model/bag_average.py
pyprocessors_opennre/opennre/model/bag_one.py
pyprocessors_opennre/opennre/model/base_model.py
pyprocessors_opennre/opennre/model/sigmoid_nn.py
pyprocessors_opennre/opennre/model/softmax_nn.py
pyprocessors_opennre/opennre/module/__init__.py
pyprocessors_opennre/opennre/module/nn/__init__.py
pyprocessors_opennre/opennre/module/nn/cnn.py
pyprocessors_opennre/opennre/module/nn/lstm.py
pyprocessors_opennre/opennre/module/nn/rnn.py
pyprocessors_opennre/opennre/module/pool/__init__.py
pyprocessors_opennre/opennre/module/pool/avg_pool.py
pyprocessors_opennre/opennre/module/pool/max_pool.py
pyprocessors_opennre/opennre/tokenization/__init__.py
pyprocessors_opennre/opennre/tokenization/basic_tokenizer.py
pyprocessors_opennre/opennre/tokenization/bert_tokenizer.py
pyprocessors_opennre/opennre/tokenization/utils.py
pyprocessors_opennre/opennre/tokenization/word_piece_tokenizer.py
pyprocessors_opennre/opennre/tokenization/word_tokenizer.py
pyprocessors_opennre-0.5.161.dist-info/entry_points.txt
pyprocessors_opennre-0.5.161.dist-info/licenses/LICENSE
pyprocessors_opennre-0.5.161.dist-info/WHEEL
pyprocessors_opennre-0.5.161.dist-info/METADATA
pyprocessors_opennre-0.5.161.dist-info/RECORD
